scrape_anime/__init__.py
scrape_anime/scrape.py
scrape_anime-1.0.0.dist-info/LICENSE
scrape_anime-1.0.0.dist-info/METADATA
scrape_anime-1.0.0.dist-info/WHEEL
scrape_anime-1.0.0.dist-info/top_level.txt
scrape_anime-1.0.0.dist-info/RECORD
