Metadata-Version: 2.1
Name: scrape-anime
Version: 1.0.0
Summary: Scrape Anime from Kissanime
Home-page: https://github.com/chunkydonut21/scrape-anime
Author: Shivam Maheshwari
Author-email: shivammahe21@gmail.com
License: UNKNOWN
Platform: UNKNOWN
Classifier: Programming Language :: Python :: 3
Classifier: License :: OSI Approved :: MIT License
Classifier: Operating System :: OS Independent
